setup.py
smithery/__init__.py
smithery.app.egg-info/PKG-INFO
smithery.app.egg-info/SOURCES.txt
smithery.app.egg-info/dependency_links.txt
smithery.app.egg-info/entry_points.txt
smithery.app.egg-info/namespace_packages.txt
smithery.app.egg-info/not-zip-safe
smithery.app.egg-info/requires.txt
smithery.app.egg-info/top_level.txt
smithery/app/__init__.py