Metadata-Version: 1.0
Name: smithery.app
Version: 0.4.1
Summary: Collect and reformat data
Home-page: http://github.com/alexamici/smithery
Author: Alessandro Amici
Author-email: alexamici@gmail.com
License: ZPL
Platform: UNKNOWN
Classifier: Development Status :: 3 - Alpha
Classifier: Environment :: Console
Classifier: Intended Audience :: Developers
Classifier: License :: OSI Approved :: Zope Public License
Classifier: Natural Language :: English
Classifier: Operating System :: OS Independent
Classifier: Programming Language :: Python
Classifier: Topic :: Utilities
